{
	"think": true,
	"caption": "An upbeat trot song with bouncy accordion melodies, cheerful brass sections, and traditional Korean percussion elements. The energetic male vocalist delivers playful verses with characteristic trot vibrato and catchy call-and-response hooks.",
	"lyrics": "[Intro]\n얼쑤! 좋다!\n\n[Verse 1]\n오늘 같은 날엔 신나게\n한잔 하면서 놀아보자\n걱정 근심 다 잊어버리고\n흥겹게 춤을 춰봐요\n\n[Chorus]\n얼쑤 좋다 신난다\n오늘 밤은 우리 세상\n쿵짝쿵짝 장단 맞춰\n모두 함께 노래해요\n라라라 랄랄라\n인생 뭐 있어 즐기자\n\n[Verse 2]\n힘든 일도 많았지만\n웃으면 복이 와요\n좋은 사람들과 함께라면\n매일이 축제야\n\n[Chorus]\n얼쑤 좋다 신난다\n오늘 밤은 우리 세상\n쿵짝쿵짝 장단 맞춰\n모두 함께 노래해요\n라라라 랄랄라\n인생 뭐 있어 즐기자\n\n[Bridge]\n자 모두 손뼉을 쳐봐요\n하나 둘 셋 넷\n\n[Outro]\n얼쑤! 좋다!\n다 같이 놀아보자!",
	"bpm": 128,
	"duration": 180,
	"keyscale": "C major",
	"language": "ko",
	"timesignature": "4"
}
