{
	"think": true,
	"caption": "A jazzy Japanese lounge track with smooth piano, upright bass, and sultry female vocals. Features sophisticated chord progressions and a late-night bar atmosphere with hints of bossa nova.",
	"lyrics": "[Intro]\n\n[Verse 1]\n煙草の煙 漂う夜\nグラスの氷が 溶けていく\nあなたの隣 座りたくて\n今夜もここに 来てしまった\n\n[Verse 2]\n視線が合って 微笑み合う\n言葉はいらない この瞬間\nジャズの調べに 身を任せて\n二人だけの 世界へ\n\n[Chorus]\n夜が更けるほど\n心が近づく\nこのまま時間よ\n止まってほしい\n\n[Verse 3]\nあなたの声が 耳に残る\n甘い囁き 忘れられない\n明日になれば 他人同士\nでも今夜だけは\n\n[Chorus]\n夜が更けるほど\n心が近づく\nこのまま時間よ\n止まってほしい\n\n[Outro]\nLast order 告げられても\nまだ帰りたくない",
	"bpm": 92,
	"duration": 240,
	"keyscale": "Eb major",
	"language": "ja",
	"timesignature": "4"
}
